streamlit_choices/__init__.py
streamlit_choices/frontend/build/asset-manifest.json
streamlit_choices/frontend/build/bootstrap.min.css
streamlit_choices/frontend/build/index.html
streamlit_choices/frontend/build/style.css
streamlit_choices/frontend/build/static/js/main.25f0700c.js
streamlit_choices/frontend/build/static/js/main.25f0700c.js.LICENSE.txt
streamlit_choices/frontend/build/static/js/main.25f0700c.js.map
streamlit_choices-0.0.6.dist-info/METADATA
streamlit_choices-0.0.6.dist-info/WHEEL
streamlit_choices-0.0.6.dist-info/top_level.txt
streamlit_choices-0.0.6.dist-info/RECORD
