Metadata-Version: 2.1
Name: streamlit-choices
Version: 0.0.6
Summary: Streamlit component that allows you to add a multiple choice question to your app.
Home-page: 
Author: Brienna Herold
Author-email: brienna.herold+pip@gmail.com
Requires-Python: >=3.8
Requires-Dist: streamlit (>=0.63)
Provides-Extra: devel
Requires-Dist: wheel ; extra == 'devel'
Requires-Dist: pytest (==7.4.0) ; extra == 'devel'
Requires-Dist: playwright (==1.36.0) ; extra == 'devel'
Requires-Dist: requests (==2.31.0) ; extra == 'devel'
Requires-Dist: pytest-playwright-snapshot (==1.0) ; extra == 'devel'
Requires-Dist: pytest-rerunfailures (==12.0) ; extra == 'devel'
